phone_sensor/__init__.py
phone_sensor/phone_sensor.py
phone_sensor/ssl-cert.pem
phone_sensor/test_phone_sensor.py
phone_sensor/js_client/asset-manifest.json
phone_sensor/js_client/index.html
phone_sensor/js_client/static/css/2.8276cb28.chunk.css
phone_sensor/js_client/static/css/2.8276cb28.chunk.css.map
phone_sensor/js_client/static/js/2.76a5d69a.chunk.js
phone_sensor/js_client/static/js/2.76a5d69a.chunk.js.LICENSE.txt
phone_sensor/js_client/static/js/2.76a5d69a.chunk.js.map
phone_sensor/js_client/static/js/main.9707d663.chunk.js
phone_sensor/js_client/static/js/main.9707d663.chunk.js.map
phone_sensor/js_client/static/js/runtime-main.98987a37.js
phone_sensor/js_client/static/js/runtime-main.98987a37.js.map
machinevision_toolbox_python.phone_sensor-1.0.4.dist-info/LICENSE
machinevision_toolbox_python.phone_sensor-1.0.4.dist-info/METADATA
machinevision_toolbox_python.phone_sensor-1.0.4.dist-info/WHEEL
machinevision_toolbox_python.phone_sensor-1.0.4.dist-info/top_level.txt
machinevision_toolbox_python.phone_sensor-1.0.4.dist-info/RECORD
