Metadata-Version: 2.1
Name: machinevision-toolbox-python.phone-sensor
Version: 1.0.4
Summary: PhoneSensor for machinevisiontoolbox. Get camera and IMU data from a camera remotely with Python
Home-page: https://github.com/CallumJHays/machinevision-toolbox-python.phone-sensor
Author: Callum Hays
Author-email: callumjhays@gmail.com
License: MIT
Project-URL: Documentation, https://github.com/CallumJHays/machinevision-toolbox-python.phone-sensor
Project-URL: Source, https://github.com/CallumJHays/machinevision-toolbox-python.phone-sensor
Project-URL: Tracker, https://github.com/CallumJHays/machinevision-toolbox-python.phone-sensor/issues
Keywords: python webapp imu motion camera machinevision computervision opencv
Platform: UNKNOWN
Classifier: Development Status :: 4 - Beta
Classifier: Intended Audience :: Developers
Classifier: License :: OSI Approved :: MIT License
Classifier: Programming Language :: Python :: 3 :: Only
Requires-Python: >=3.6
Requires-Dist: pyqrcode
Requires-Dist: websockets
Requires-Dist: numpy
Requires-Dist: typing-extensions
Provides-Extra: pil
Requires-Dist: Pillow ; extra == 'pil'
Provides-Extra: matplotlib
Requires-Dist: matplotlib ; extra == 'matplotlib'
Provides-Extra: opencv
Requires-Dist: opencv-python ; extra == 'opencv'
